{
    "marcos_narrativos": [
        {"marco": "Innovación Responsable", "descripcion": "Comunica avances tecnológicos con foco en impacto social.", "ejemplos": ["Lanzamiento de producto con enfoque sostenible"]},
        {"marco": "Comunidad Local", "descripcion": "Historias centradas en experiencias de usuarios y eventos locales.", "ejemplos": ["Evento comunitario en tienda"]}
    ],
    "resumen_marcos": "La marca usa marcos centrados en innovación con énfasis en sostenibilidad y en el vínculo con la comunidad."
}